icusim/__init__.py
icusim/icu_burden_simulator.py
icusim/params.py
icusim/stats_to_dataframe.py
icusim/utils.py
icusim/commands/MonteCarlo.py
icusim/commands/SobolSensitivity.py
icusim/commands/__init__.py
ICUSIM-0.2.0.dist-info/LICENSE
ICUSIM-0.2.0.dist-info/METADATA
ICUSIM-0.2.0.dist-info/WHEEL
ICUSIM-0.2.0.dist-info/top_level.txt
ICUSIM-0.2.0.dist-info/RECORD
